uaclient/__init__.py
uaclient/application_certificate_dialog.py
uaclient/applicationcertificate_ui.py
uaclient/connection_dialog.py
uaclient/connection_ui.py
uaclient/graphwidget.py
uaclient/mainwindow.py
uaclient/mainwindow_ui.py
uaclient/uaclient.py
uaclient/theme/__init__.py
uaclient/theme/breeze_resources.py
opcua_client-0.8.4.dist-info/LICENSE
opcua_client-0.8.4.dist-info/METADATA
opcua_client-0.8.4.dist-info/WHEEL
opcua_client-0.8.4.dist-info/entry_points.txt
opcua_client-0.8.4.dist-info/top_level.txt
opcua_client-0.8.4.dist-info/RECORD
