Metadata-Version: 1.0
Name: opcua-client
Version: 0.8.4
Summary: OPC-UA Client GUI
Home-page: https://github.com/FreeOpcUa/opcua-client-gui
Author: Olivier R-D
Author-email: UNKNOWN
License: GNU General Public License
Platform: UNKNOWN
